cache/__init__.py
cache/config.py
cache/coordinator.py
cache/firestore.py
cache/freshness.py
cache/integration.py
cache/keys.py
cache/manifest.py
cache/memory.py
cli/__init__.py
cli/auth.py
cli/main.py
cli/output.py
generated/__init__.py
generated/dashboard_types.py
generated/format_types.py
generated/widget_types.py
services/__init__.py
services/activity.py
services/auth.py
services/context.py
services/dashboards.py
services/export.py
services/manifest.py
services/queries.py
services/quick_metrics.py
services/render.py
services/schedules.py
services/time_scope.py
auth.py
mf_engine.py
settings.py
storage.py
warehouse.py
metricly_cli-0.1.19.dist-info/METADATA
metricly_cli-0.1.19.dist-info/WHEEL
metricly_cli-0.1.19.dist-info/entry_points.txt
metricly_cli-0.1.19.dist-info/RECORD
