Metadata-Version: 2.4
Name: metricly-cli
Version: 0.1.19
Summary: Metricly CLI - Query metrics and manage dashboards from the terminal
Project-URL: Homepage, https://metricly.xyz
Project-URL: Documentation, https://metricly.xyz/docs
Author-email: Metricly <support@metricly.xyz>
License: Proprietary
Keywords: analytics,bi,dashboard,dbt,metricflow,metrics
Classifier: Development Status :: 4 - Beta
Classifier: Environment :: Console
Classifier: Intended Audience :: Developers
Classifier: Intended Audience :: Science/Research
Classifier: License :: Other/Proprietary License
Classifier: Operating System :: OS Independent
Classifier: Programming Language :: Python :: 3
Classifier: Programming Language :: Python :: 3.12
Classifier: Topic :: Database
Classifier: Topic :: Scientific/Engineering :: Information Analysis
Requires-Python: >=3.12
Requires-Dist: cachetools>=5.0.0
Requires-Dist: dbt-bigquery>=1.9.0
Requires-Dist: dbt-duckdb>=1.10.0
Requires-Dist: dbt-metricflow>=0.8.0
Requires-Dist: duckdb>=1.0.0
Requires-Dist: firebase-admin>=6.0.0
Requires-Dist: google-auth-oauthlib>=1.0.0
Requires-Dist: google-auth>=2.0.0
Requires-Dist: google-cloud-bigquery>=3.0.0
Requires-Dist: google-cloud-firestore>=2.0.0
Requires-Dist: google-cloud-secret-manager>=2.26.0
Requires-Dist: google-cloud-storage>=2.0.0
Requires-Dist: httpx>=0.27.0
Requires-Dist: pychrome>=0.2.4
Requires-Dist: pydantic-settings>=2.0.0
Requires-Dist: pydantic>=2.12.5
Requires-Dist: python-dateutil>=2.8.0
Requires-Dist: pyyaml>=6.0.3
Requires-Dist: rich>=13.0.0
Requires-Dist: typer>=0.12.0
